timeseriesai/__init__.py
timeseriesai/version.py
TimeSeriesAI-0.0.0.dist-info/LICENSE
TimeSeriesAI-0.0.0.dist-info/METADATA
TimeSeriesAI-0.0.0.dist-info/WHEEL
TimeSeriesAI-0.0.0.dist-info/top_level.txt
TimeSeriesAI-0.0.0.dist-info/RECORD
