Metadata-Version: 2.1
Name: TimeSeriesAI
Version: 0.0.0
Summary: AI for Time Series
Author-email: Wenjie Du <wdu@time-series.ai>
License: Apache License
Project-URL: Source, https://github.com/WenjieDu/AI4TS
Project-URL: Homepage, https://time-series.ai
Keywords: data science,data mining,neural networks,machine learning,deep learning,artificial intelligence,time-series analysis,time series,imputation,interpolation,classification,clustering,forecasting,partially observed,irregular sampled,partially-observed time series,incomplete time series
Classifier: Development Status :: 5 - Production/Stable
Classifier: Intended Audience :: Developers
Classifier: Intended Audience :: Education
Classifier: Intended Audience :: Science/Research
Classifier: Intended Audience :: Healthcare Industry
Classifier: License :: OSI Approved :: Apache Software License
Classifier: Operating System :: OS Independent
Classifier: Programming Language :: Python :: 3
Classifier: Programming Language :: Python :: 3.8
Classifier: Programming Language :: Python :: 3.9
Classifier: Programming Language :: Python :: 3.10
Classifier: Programming Language :: Python :: 3.11
Classifier: Topic :: Scientific/Engineering :: Artificial Intelligence
Classifier: Topic :: Software Development :: Libraries :: Application Frameworks
Requires-Python: >=3.8
License-File: LICENSE
